fastrpc/__init__.py
fastrpc/fastrpc.py
fastrpc_py-0.1.3.dist-info/METADATA
fastrpc_py-0.1.3.dist-info/WHEEL
fastrpc_py-0.1.3.dist-info/top_level.txt
fastrpc_py-0.1.3.dist-info/RECORD
