Metadata-Version: 2.4
Name: fastrpc-py
Version: 0.1.3
Summary: Add your description here
Author-email: xingshuyin <xing-shuyin@qq.com>
License: MIT
Requires-Python: >=3.10
Requires-Dist: fastapi>=0.117.1
Requires-Dist: python-multipart>=0.0.20
Requires-Dist: requests>=2.32.5
Requires-Dist: setuptools>=80.9.0
Requires-Dist: uvicorn[standard]>=0.37.0
